radioactiveshrimp/__init__.py
radioactiveshrimp/_core.abi3.so
radioactiveshrimp/_core.pyi
radioactiveshrimp/deepl/__init__.py
radioactiveshrimp/deepl/two_layer_binary_classification.py
radioactiveshrimp/differential/__init__.py
radioactiveshrimp/differential/discrete.py
radioactiveshrimp/distributions/__init__.py
radioactiveshrimp/distributions/cvdistributions.py
radioactiveshrimp/matrix/__init__.py
radioactiveshrimp/matrix/elementary.py
radioactiveshrimp/model/__init__.py
radioactiveshrimp/model/logit.py
radioactiveshrimp/model/neuralnet.py
radioactiveshrimp/model/regression.py
radioactiveshrimp/model/saved_model.onnx
radioactiveshrimp/py.typed
radioactiveshrimp-0.1.13.dist-info/METADATA
radioactiveshrimp-0.1.13.dist-info/WHEEL
radioactiveshrimp-0.1.13.dist-info/RECORD
